CHANGES.rst
MANIFEST.in
README.rst
setup.py
invisibleroads_sockets/__init__.py
invisibleroads_sockets.egg-info/PKG-INFO
invisibleroads_sockets.egg-info/SOURCES.txt
invisibleroads_sockets.egg-info/dependency_links.txt
invisibleroads_sockets.egg-info/not-zip-safe
invisibleroads_sockets.egg-info/pbr.json
invisibleroads_sockets.egg-info/requires.txt
invisibleroads_sockets.egg-info/top_level.txt