Metadata-Version: 1.1
Name: invisibleroads-sockets
Version: 0.1.1
Summary: Sockets for distributed processes
Home-page: http://invisibleroads.com
Author: Roy Hyunjin Han
Author-email: rhh@crosscompute.com
License: UNKNOWN
Keywords: invisibleroads
Platform: UNKNOWN
Classifier: Programming Language :: Python
Classifier: License :: OSI Approved :: MIT License
